odoo/addons/partner_risk_insurance_security/README.rst
odoo/addons/partner_risk_insurance_security/__init__.py
odoo/addons/partner_risk_insurance_security/__manifest__.py
odoo/addons/partner_risk_insurance_security/i18n/it.po
odoo/addons/partner_risk_insurance_security/i18n/partner_risk_insurance_security.pot
odoo/addons/partner_risk_insurance_security/models/__init__.py
odoo/addons/partner_risk_insurance_security/models/res_partner.py
odoo/addons/partner_risk_insurance_security/readme/CONTRIBUTORS.rst
odoo/addons/partner_risk_insurance_security/readme/DESCRIPTION.rst
odoo/addons/partner_risk_insurance_security/readme/USAGE.rst
odoo/addons/partner_risk_insurance_security/security/groups.xml
odoo/addons/partner_risk_insurance_security/static/icon.png
odoo/addons/partner_risk_insurance_security/static/description/icon.png
odoo/addons/partner_risk_insurance_security/static/description/index.html
odoo/addons/partner_risk_insurance_security/tests/__init__.py
odoo/addons/partner_risk_insurance_security/tests/test_partner_risk_insurance_security.py
odoo/addons/partner_risk_insurance_security/views/res_partner_view.xml
odoo14_addon_partner_risk_insurance_security-14.0.1.0.1.dev4.dist-info/METADATA
odoo14_addon_partner_risk_insurance_security-14.0.1.0.1.dev4.dist-info/WHEEL
odoo14_addon_partner_risk_insurance_security-14.0.1.0.1.dev4.dist-info/top_level.txt
odoo14_addon_partner_risk_insurance_security-14.0.1.0.1.dev4.dist-info/RECORD
