Metadata-Version: 2.1
Name: odoo14-addon-partner_risk_insurance_security
Version: 14.0.1.0.1.dev4
Summary: Risk insurance partner information are accessible onlybeing part of the Full Access to Credit Policy State group
Home-page: https://github.com/OCA/credit-control
Author: Ooops404,toita86,Odoo Community Association (OCA)
Author-email: support@odoo-community.org
License: AGPL-3
Classifier: Programming Language :: Python
Classifier: Framework :: Odoo
Classifier: Framework :: Odoo :: 14.0
Classifier: License :: OSI Approved :: GNU Affero General Public License v3
Requires-Python: >=3.6
Requires-Dist: odoo14-addon-partner-risk-insurance
Requires-Dist: odoo<14.1dev,>=14.0a
